restbase/__init__.py
restbase/__main__.py
restbase/api.py
restbase/cli.py
restbase/config.py
restbase/config_generator.py
restbase/db.py
restbase/schema.py
restbase_cli-0.0.2.dist-info/licenses/LICENSE
restbase_cli-0.0.2.dist-info/METADATA
restbase_cli-0.0.2.dist-info/WHEEL
restbase_cli-0.0.2.dist-info/entry_points.txt
restbase_cli-0.0.2.dist-info/top_level.txt
restbase_cli-0.0.2.dist-info/RECORD
