Metadata-Version: 2.4
Name: restbase-cli
Version: 0.0.2
Summary: Sync any REST API to PostgreSQL with schema inference
Author-email: Soumyadeep Das <soumyadeep.das423@gmail.com>
License: MIT
Project-URL: Homepage, https://github.com/soumyadeep423/RestBase
Requires-Python: >=3.7
License-File: LICENSE
Requires-Dist: requests
Requires-Dist: psycopg2-binary
Requires-Dist: pyyaml
Dynamic: license-file
